isayhello/__init__.py
isayhello/say.py
isayhello-0.1.0.dist-info/METADATA
isayhello-0.1.0.dist-info/WHEEL
isayhello-0.1.0.dist-info/entry_points.txt
isayhello-0.1.0.dist-info/RECORD
